{
	"configurations" : 
	[
		{
			"directories" : 
			[
				{
					"build" : ".",
					"hasInstallRule" : true,
					"jsonFile" : "directory-.-Debug-29009735fdb8eaf86d21.json",
					"minimumCMakeVersion" : 
					{
						"string" : "3.1.0"
					},
					"projectIndex" : 0,
					"source" : ".",
					"targetIndexes" : 
					[
						0,
						1
					]
				}
			],
			"name" : "Debug",
			"projects" : 
			[
				{
					"directoryIndexes" : 
					[
						0
					],
					"name" : "QRencode",
					"targetIndexes" : 
					[
						0,
						1
					]
				}
			],
			"targets" : 
			[
				{
					"directoryIndex" : 0,
					"id" : "qrenc::@6890427a1f51a3e7e1df",
					"jsonFile" : "target-qrenc-Debug-4776c7e3b90a0699661f.json",
					"name" : "qrenc",
					"projectIndex" : 0
				},
				{
					"directoryIndex" : 0,
					"id" : "qrencode::@6890427a1f51a3e7e1df",
					"jsonFile" : "target-qrencode-Debug-acc716d629ccfc5121c9.json",
					"name" : "qrencode",
					"projectIndex" : 0
				}
			]
		}
	],
	"kind" : "codemodel",
	"paths" : 
	{
		"build" : "E:/Developments/QREncoder/build",
		"source" : "E:/Developments/QREncoder"
	},
	"version" : 
	{
		"major" : 2,
		"minor" : 7
	}
}
